[
  {
    "logo": "https://raw.githubusercontent.com/tiviku69/apk/refs/heads/main/g.jpg",
    "lnk": "https://tiviku69.github.io/apk/m3u/cpts1.m3u8",
    "ttl": "Captain Tsubasa: Road to (2002) dubbing",
    "z": "z",
    "z2": "z2",
    "z3": "z3",
    "z4": "z4",
    "z5": "z5",
    "tiviku": "apk"
   },
   {
    "logo": "https://raw.githubusercontent.com/tiviku69/apk/refs/heads/main/g.jpg",
    "lnk": "https://tiviku69.github.io/apk/m3u/cpts2.m3u8",
    "htm": "ply.html",
    "ttl": "Captain Tsubasa: Road to (2002) dubbing",
    "eps": "eps 2"
   },
   {
    "logo": "https://raw.githubusercontent.com/tiviku69/apk/refs/heads/main/g.jpg",
    "lnk": "https://tiviku69.github.io/apk/m3u/cpts3.m3u8",
    "htm": "ply/1.html",
    "ttl": "Captain Tsubasa: Road to (2002) dubbing",
    "eps": "eps 3"
   },
   {
    "logo": "https://raw.githubusercontent.com/tiviku69/apk/refs/heads/main/g.jpg",
    "lnk": "https://tiviku69.github.io/apk/m3u/cpts4.m3u8",
    "htm": "ply/1.html",
    "ttl": "Captain Tsubasa: Road to (2002) dubbing",
    "eps": "eps 4"
   },
   {
    "logo": "https://raw.githubusercontent.com/tiviku69/apk/refs/heads/main/g.jpg",
    "lnk": "https://tiviku69.github.io/apk/m3u/cpts5.m3u8",
    "htm": "ply/1.html",
    "ttl": "Captain Tsubasa: Road to (2002) dubbing",
    "eps": "eps 5"
   },
   {
    "logo": "https://raw.githubusercontent.com/tiviku69/apk/refs/heads/main/g.jpg",
    "lnk": "https://tiviku69.github.io/apk/m3u/cpts6.m3u8",
    "htm": "ply/1.html",
    "ttl": "Captain Tsubasa: Road to (2002) dubbing",
    "eps": "eps 6"
   },
   {
    "logo": "https://raw.githubusercontent.com/tiviku69/apk/refs/heads/main/g.jpg",
    "lnk": "https://tiviku69.github.io/apk/m3u/cpts7.m3u8",
    "htm": "ply/1.html",
    "ttl": "Captain Tsubasa: Road to (2002) dubbing",
    "eps": "eps 7"
   },
   {
    "logo": "https://raw.githubusercontent.com/tiviku69/apk/refs/heads/main/g.jpg",
    "lnk": "https://tiviku69.github.io/apk/m3u/cpts8.m3u8",
    "htm": "ply/1.html",
    "ttl": "Captain Tsubasa: Road to (2002) dubbing",
    "eps": "eps 8"
   },
   {
    "logo": "https://raw.githubusercontent.com/tiviku69/apk/refs/heads/main/g.jpg",
    "lnk": "https://tiviku69.github.io/apk/m3u/cpts9.m3u8",
    "htm": "ply/1.html",
    "ttl": "Captain Tsubasa: Road to (2002) dubbing",
    "eps": "eps 9"
   },
   {
    "logo": "https://raw.githubusercontent.com/tiviku69/apk/refs/heads/main/g.jpg",
    "lnk": "https://tiviku69.github.io/apk/m3u/cpts10.m3u8",
    "htm": "ply/1.html",
    "ttl": "Captain Tsubasa: Road to (2002) dubbing",
    "eps": "eps 10"
   }
]
